{
  "date": "2025-12-04",
  "date_range": {
    "start": "2025-11-28",
    "end": "2025-12-04"
  },
  "generated_at": "2026-05-03T02:46:05.921095Z",
  "highlights": [
    {
      "rank": 1,
      "type": "top_event",
      "event_id": "pvh-2025-12-04-062",
      "date": "2025-12-04",
      "title": "PVH Corp (PVH) Q3 2025 Earnings Call Highlights: Navigating Challenges with Strategic Growth - Yahoo Finance",
      "importance_score": 0.75
    }
  ],
  "anomalies_7d": [],
  "topic_7d_summary": {
    "fast_fashion": {
      "this_week": 3,
      "last_week": 1,
      "week_over_week_change": "+200%",
      "sentiment_this_week": 0.0
    },
    "earnings": {
      "this_week": 1,
      "last_week": 3,
      "week_over_week_change": "-67%",
      "sentiment_this_week": 0.5
    }
  },
  "company_7d_summary": {
    "inditex": {
      "event_count": 5,
      "sentiment_avg": 0.1,
      "rank": 1
    },
    "pvh": {
      "event_count": 1,
      "sentiment_avg": 0.5,
      "rank": 2
    }
  },
  "comparisons": {
    "vs_last_week": {
      "event_count": {
        "this": 6,
        "last": 4,
        "change_pct": 50.0
      }
    }
  },
  "daily_breakdown": [
    {
      "date": "2025-11-28",
      "event_count": 2,
      "sentiment_avg": 0
    },
    {
      "date": "2025-11-29",
      "event_count": 0,
      "sentiment_avg": 0
    },
    {
      "date": "2025-11-30",
      "event_count": 0,
      "sentiment_avg": 0
    },
    {
      "date": "2025-12-01",
      "event_count": 0,
      "sentiment_avg": 0
    },
    {
      "date": "2025-12-02",
      "event_count": 0,
      "sentiment_avg": 0
    },
    {
      "date": "2025-12-03",
      "event_count": 3,
      "sentiment_avg": 0
    },
    {
      "date": "2025-12-04",
      "event_count": 1,
      "sentiment_avg": 0
    }
  ]
}